ez_setup.py
setup.py
config/capp30121-aut-18.yml
config/capp30121-aut-19.yml
config/capp30122-win-18.yml
config/capp30122-win-19.yml
config/cmsc12100-aut-17.yml
config/cmsc12100-aut-18.yml
config/cmsc12100-aut-19.yml
config/cmsc12200-win-18.yml
config/cmsc12200-win-19.yml
config/cmsc12300-spr-17.yml
config/cmsc12300-spr-18.yml
config/cmsc12300-spr-19.yml
config/cs121-aut-15-testing.yml
config/cs121-aut-15.yml
config/cs121-aut-16-testing.yml
config/cs121-aut-16.yml
config/cs122-win-16.yml
config/cs122-win-17.yml
src/uchicago_cs_setup_script/__init__.py
src/uchicago_cs_setup_script/script.py
src/uchicago_cs_setup_script.egg-info/PKG-INFO
src/uchicago_cs_setup_script.egg-info/SOURCES.txt
src/uchicago_cs_setup_script.egg-info/dependency_links.txt
src/uchicago_cs_setup_script.egg-info/entry_points.txt
src/uchicago_cs_setup_script.egg-info/not-zip-safe
src/uchicago_cs_setup_script.egg-info/requires.txt
src/uchicago_cs_setup_script.egg-info/top_level.txt