Metadata-Version: 2.1
Name: uchicago-cs-setup-script
Version: 1.0.1
Summary: A setup script for CS courses at the University of Chicago
Home-page: http://people.cs.uchicago.edu/~borja/
Author: Borja Sotomayor
Author-email: borja@cs.uchicago.edu
License: BSD
Platform: UNKNOWN
Classifier: Development Status :: 4 - Beta
Classifier: Environment :: Console
Classifier: Intended Audience :: Developers
Classifier: Intended Audience :: Science/Research
Classifier: Intended Audience :: Education
Classifier: License :: OSI Approved :: BSD License
Classifier: Operating System :: POSIX
Classifier: Programming Language :: Python :: 3
Classifier: Programming Language :: Python :: 3 :: Only
Provides-Extra: ssh
